imalign/__init__.py
imalign/align.py
imalign/main.py
imalign-0.0.5.dist-info/LICENSE
imalign-0.0.5.dist-info/METADATA
imalign-0.0.5.dist-info/WHEEL
imalign-0.0.5.dist-info/entry_points.txt
imalign-0.0.5.dist-info/top_level.txt
imalign-0.0.5.dist-info/RECORD
