Metadata-Version: 2.1
Name: imalign
Version: 0.0.5
Summary: Align a source image file with a reference image
Author-email: Roman <roman@vintage-camera.pictures>
Project-URL: Homepage, https://github.com/vintage-camera-pictures/imalign
Project-URL: Bug Tracker, https://github.com/vintage-camera-pictures/imalign/issues
Keywords: image align
Classifier: Programming Language :: Python :: 3
Classifier: License :: OSI Approved :: GNU General Public License v3 (GPLv3)
Classifier: Operating System :: OS Independent
Requires-Python: >=3.7
License-File: LICENSE
Requires-Dist: numpy (>=1.23.4)
Requires-Dist: opencv-contrib-python-headless (>=4.6.0.66)
